[
    {
        "suggestion": "cdmvndfmnvmdfmv",
        "action": "like",
        "timestamp": "2026-07-14T16:55:49.606991"
    },
    {
        "suggestion": "I'm curious, what emerging AI/ML trend do you think will have the biggest impact in the next year?",
        "action": "like",
        "timestamp": "2026-07-14T16:55:56.075705"
    },
    {
        "suggestion": "Beyond the hype, what's a practical technology challenge you see AI/ML best positioned to solve today?",
        "action": "dislike",
        "timestamp": "2026-07-14T16:56:16.584278"
    },
    {
        "suggestion": "What's one thing in AI or ML you're particularly excited about learning more about right now?",
        "action": "like",
        "timestamp": "2026-07-14T16:56:19.664516"
    }
]